AUTHORS
COPYING
MANIFEST.in
README
setup.py
moksha/__init__.py
moksha.common.egg-info/PKG-INFO
moksha.common.egg-info/SOURCES.txt
moksha.common.egg-info/dependency_links.txt
moksha.common.egg-info/entry_points.txt
moksha.common.egg-info/namespace_packages.txt
moksha.common.egg-info/pbr.json
moksha.common.egg-info/requires.txt
moksha.common.egg-info/top_level.txt
moksha/common/__init__.py
moksha/common/config.py
moksha/common/commands/__init__.py
moksha/common/commands/cli.py
moksha/common/exc/__init__.py
moksha/common/lib/__init__.py
moksha/common/lib/cache.py
moksha/common/lib/converters.py
moksha/common/lib/dates.py
moksha/common/lib/helpers.py
moksha/common/tests/__init__.py
moksha/common/tests/test_config.ini
moksha/common/tests/test_config.py
moksha/common/tests/test_helpers.py
moksha/common/testtools/__init__.py
moksha/common/testtools/utils.py
moksha/common/utils/__init__.py