Metadata-Version: 1.1
Name: moksha.common
Version: 1.2.4
Summary: Common components for Moksha
Home-page: http://moksha.fedorahosted.org
Author: Luke Macken, John (J5) Palmieri, Mairin Duffy, and Ralph Bean
Author-email: UNKNOWN
License: UNKNOWN
Platform: UNKNOWN
Classifier: Development Status :: 5 - Production/Stable
Classifier: Intended Audience :: Developers
Classifier: License :: OSI Approved :: Apache Software License
Classifier: Topic :: Software Development :: Libraries :: Python Modules
Classifier: Programming Language :: Python :: 2.6
Classifier: Programming Language :: Python :: 2.7
Classifier: Programming Language :: Python :: 3
Classifier: Programming Language :: Python :: 3.2
Classifier: Programming Language :: Python :: 3.3
